Metadata-Version: 2.1
Name: warp10-pywarp
Version: 1.0.1
Summary: A set of functions to ease working with Warp 10
Home-page: http://github.com/senx/pywarp
Author: SenX
Author-email: contact@senx.io
License: Apache 2.0
Keywords: time series Warp 10
Platform: UNKNOWN
Classifier: Development Status :: 5 - Production/Stable
Classifier: Intended Audience :: Developers
Classifier: Topic :: Scientific/Engineering
Classifier: Programming Language :: Python
Classifier: Programming Language :: Python :: 3.8
Requires-Python: >=3.8
